{"annonsId": 24518647, "kallaTyp": "VIA_ANNONSERA", "version": "2.0", "annonsrubrik": "Hej Servit\u00f6r/Servitris!", "annonstext": "Hej Service!\n\nVi p\u00e5 Rollin Bistros ut\u00f6kar i \u00e5r med en st\u00f6rre uteservering p\u00e5 Lindholmen och forts\u00e4tter expandera i v\u00e5r urbana restaurang i Gamlestaden och s\u00f6ker nu dig som gillar att ge bra service p\u00e5 ett l\u00e4ttsamt men \u00e4nd\u00e5 seri\u00f6st s\u00e4tt.\n\nHos dig s\u00f6ker vi f\u00f6ljande egenskaper: \n\nDu har ett \u00f6ga f\u00f6r vad som ska g\u00f6ras f\u00f6r att restaurangen ska ha en hel och ren k\u00e4nsla. \n\nDu \u00e4r Sj\u00e4lvg\u00e5ende.\n\nDu \u00e4r noga med tider.\n\nDu v\u00e4rdes\u00e4tter dina kollegor och arbetsplats. \n\nDu har h\u00f6g arbetsmoral. \n\nDu gillar att ge det lilla extra f\u00f6r g\u00e4sten\n\nPositiv energi\n\nInom Rollin Bistros \u00e4r vi ett glatt och drivet g\u00e4ng som gillar det vi g\u00f6r, och vi s\u00f6ker efter likasinnade. \n\nTj\u00e4nsten kommer mestadels best\u00e5 av kv\u00e4lls jobb fr\u00e5n ca 15.00-22.30 Ons-L\u00f6r. Med m\u00f6jlighet till dagtid under Lunch. \n\nTidigare erfarenheter som vi ser \u00e4r ett plus:\n\n-Kassa vana\n\n-Serverings vana\n\n-Hantera m\u00e5nga g\u00e4ster samtidigt\n\n-Bas kunskaper om vin & \u00f6l.\n\nTj\u00e4nsten \u00e4r tillg\u00e4nglig from April / Maj tom 31 September \n\nKolla in v\u00e5r instagram f\u00f6r att f\u00e5 en bra bild av oss som helhet! @rollinbistros", "annonstextFormaterad": "<p>Hej Service!</p><p>Vi p\u00e5 Rollin Bistros ut\u00f6kar i \u00e5r med en st\u00f6rre uteservering p\u00e5 Lindholmen och forts\u00e4tter expandera i v\u00e5r urbana restaurang i Gamlestaden och s\u00f6ker nu dig som gillar att ge bra service p\u00e5 ett l\u00e4ttsamt men \u00e4nd\u00e5 seri\u00f6st s\u00e4tt.</p><p>Hos dig s\u00f6ker vi f\u00f6ljande egenskaper: </p><p>Du har ett \u00f6ga f\u00f6r vad som ska g\u00f6ras f\u00f6r att restaurangen ska ha en hel och ren k\u00e4nsla. </p><p>Du \u00e4r Sj\u00e4lvg\u00e5ende.</p><p>Du \u00e4r noga med tider.</p><p>Du v\u00e4rdes\u00e4tter dina kollegor och arbetsplats. </p><p>Du har h\u00f6g arbetsmoral. </p><p>Du gillar att ge det lilla extra f\u00f6r g\u00e4sten</p><p>Positiv energi</p><p>Inom Rollin Bistros \u00e4r vi ett glatt och drivet g\u00e4ng som gillar det vi g\u00f6r, och vi s\u00f6ker efter likasinnade. </p><p>Tj\u00e4nsten kommer mestadels best\u00e5 av kv\u00e4lls jobb fr\u00e5n ca 15.00-22.30 Ons-L\u00f6r. Med m\u00f6jlighet till dagtid under Lunch. </p><p>Tidigare erfarenheter som vi ser \u00e4r ett plus:</p><p>-Kassa vana</p><p>-Serverings vana</p><p>-Hantera m\u00e5nga g\u00e4ster samtidigt</p><p>-Bas kunskaper om vin &amp; \u00f6l.</p><p><br></p><p>Tj\u00e4nsten \u00e4r tillg\u00e4nglig from April / Maj tom 31 September </p><p>Kolla in v\u00e5r instagram f\u00f6r att f\u00e5 en bra bild av oss som helhet! @rollinbistros</p>", "publiceringsdatum": "2021-02-09 00:00:00", "sistaPubliceringsdatum": "2021-04-11 23:59:59", "sistaAnsokningsdatum": "2021-04-11 23:59:59", "avpublicerad": false, "antalPlatser": 2, "webbadress": "www.rollinbistros.se", "anstallningTyp": {"varde": "PFZr_Syz_cUq", "namn": "Vanlig anst\u00e4llning"}, "varaktighetTyp": {"varde": "a7uU_j21_mkL", "namn": "Tillsvidare"}, "arbetstidTyp": {"varde": "947z_JGS_Uk2", "namn": "Deltid"}, "arbetstidOmfattningFran": 50.0, "arbetstidOmfattningTill": 100.0, "lonTyp": {"varde": "oG8G_9cW_nRf", "namn": "Fast m\u00e5nads- vecko- eller timl\u00f6n"}, "organisationsnummer": "5591391320", "arbetsgivareId": "21138841", "arbetsgivareNamn": "Rollin Business AB", "arbetsplatsId": "86644760", "arbetsplatsNamn": "Rollin Bistros ", "ansokningssattEpost": " EMAIL ", "ansokningssattViaAF": false, "ejKravSvenskaEngelska": false, "inkluderande": false, "referens": "Hej Service ", "yrkesroll": {"varde": "rGGf_KLs_To7", "namn": "Servit\u00f6r/Servitris"}, "ingenErfarenhetKravs": false, "yrkeserfarenheter": [{"varde": "rGGf_KLs_To7", "namn": "Servit\u00f6r/Servitris", "vikt": 5, "erfarenhetsniva": {"varde": "LLnd_5GJ_4ju", "namn": "1-2 \u00e5rs erfarenhet"}}], "tillgangTillEgenBil": false, "sprak": [{"varde": "NVxJ_hLg_TYS", "namn": "Engelska", "vikt": 10}, {"varde": "zSLA_vw2_FXN", "namn": "Svenska", "vikt": 10}], "uppdateradTid": 1616579219576, "arbetsplatsadress": {"gatuadress": "Lindholmspiren 9 / Gamlestadsv\u00e4gen 4", "postnr": "41756", "postort": "G\u00d6TEBORG", "land": {"varde": "i46j_HmG_v64", "namn": "Sverige"}, "lan": {"varde": "zdoY_6u5_Krt", "namn": "V\u00e4stra G\u00f6talands l\u00e4n"}, "kommun": {"varde": "PVZL_BQT_XtL", "namn": "G\u00f6teborg"}, "latitud": "57.7054305145435", "longitud": "11.9386333452828", "koordinatPrecision": "POSTNUMMER"}, "informationAnsokningssatt": null, "telefonnummer": null, "kontaktpersoner": [{"fornamn": "Testy", "efternamn": "Testsson", "befattning": null, "telefonnummer": "+01011122233", "epost": "test@jobtechdev.se", "fackligRepresentant": false, "beskrivning": "blabla"}]}