{"annonsId": 24606375, "kallaTyp": "VIA_PLATSBANKEN_DXA", "version": "1.0", "externtAnnonsId": "46-556576-4668-1102531-1", "annonsrubrik": "Software Developer, Medtech", "annonstext": "i3tex utvecklingsteam inriktat mot produktutveckling inom Life Science och framf\u00f6r allt Medicinteknik letar efter nya kollegor! \ud83d\udca5 Potential och attityd v\u00e4ger alltid tung hos oss, liksom v\u00e5rt fokus p\u00e5 att bygga dynamiska och starka kunskapsteam internt. Men just nu beh\u00f6ver du \u00e4ven ha med dig n\u00e5gra \u00e5rs erfarenhet inom mjukvaruutveckling C, C++ och/eller C#.\n\n3 goda anledningar till att vi anst\u00e4ller NU \ud83d\ude80\n\n- Innovation och tillv\u00e4xt st\u00e5r h\u00f6gt upp p\u00e5 2021 \u00e5rs i3tex-agenda\n- Stolen mellan v\u00e5ra tv\u00e5 mest erfarna mjukvaruutvecklare \u00e4r ledig\n- Med fler kreativa probleml\u00f6sare och tech entusiaster kan vi hj\u00e4lpa fler fantastiska kunder att l\u00f6sa komplexa teknikutmaningar som g\u00f6r verklig skillnad i m\u00e4nniskor liv!\nJust nu finns stora m\u00f6jligheter att direkt involveras i sp\u00e4nnande uppdrag, antingen p\u00e5 plats hos v\u00e5ra kunder eller in-house p\u00e5 i3tex kontor vid Klippan i G\u00f6teborg.\n\nF\u00f6rutom din erfarenhet och intresse f\u00f6r kod tror vi att du \u00e4r kreativ, kommunikativ och har ett \u00f6ga f\u00f6r detaljer. D\u00e5 vi jobbar med medicintekniska produkter och l\u00f6sningar \u00e4r dokumentation och regelefterlevnad viktiga delar f\u00f6r att s\u00e4kerst\u00e4lla dess kvalitet i alla led. D\u00e4rmed \u00e4r ett visst m\u00e5tt av t\u00e5lamod en klar f\u00f6rdel. \u2b50\n\nOM OSS\n\ni3tex \u00e4r ett visions- och v\u00e4rderingsstyrt tekniskt konsultbolag inom produktutveckling och tillsammans med v\u00e5ra kunder utvecklar vi framtidens produkter f\u00f6r en b\u00e4ttre v\u00e4rld. Vi tror p\u00e5 en stark f\u00f6retagskultur, att hj\u00e4lpa varandra att lyckas och att ha roligt tillsammans! Idag \u00e4r vi 170 medarbetare f\u00f6rdelat p\u00e5 6 kontor runtom i Sverige. V\u00e5ra kunder \u00e5terfinns inom Automotive, Medical Technology, IT & Digital Solutions, Aerospace och Industry. De tre i:en i i3tex st\u00e5r for Innovate, Implement, Improve!\n\nVill du st\u00e4lla fr\u00e5gor om tj\u00e4nsten eller om oss som f\u00f6retag kan du kontakta aff\u00e4rs- och medarbetaransvarig FIRSTNAME LASTNAME och har du fackliga fr\u00e5gor kan du kontakta n\u00e5gon av v\u00e5ra fackliga representanter via v\u00e4xeln  TELEPHONENO .\n\nVi ser fram emot din ans\u00f6kan!\n\nKontakt\n\nFIRSTNAME LASTNAME,  TELEPHONENO ", "annonstextFormaterad": "i3tex utvecklingsteam inriktat mot produktutveckling inom Life Science och framf\u00f6r allt Medicinteknik letar efter nya kollegor! \ud83d\udca5 Potential och attityd v\u00e4ger alltid tung hos oss, liksom v\u00e5rt fokus p\u00e5 att bygga dynamiska och starka kunskapsteam internt. Men just nu beh\u00f6ver du \u00e4ven ha med dig n\u00e5gra \u00e5rs erfarenhet inom mjukvaruutveckling C, C++ och/eller C#.\n\n3 goda anledningar till att vi anst\u00e4ller NU \ud83d\ude80\n\n- Innovation och tillv\u00e4xt st\u00e5r h\u00f6gt upp p\u00e5 2021 \u00e5rs i3tex-agenda\n- Stolen mellan v\u00e5ra tv\u00e5 mest erfarna mjukvaruutvecklare \u00e4r ledig\n- Med fler kreativa probleml\u00f6sare och tech entusiaster kan vi hj\u00e4lpa fler fantastiska kunder att l\u00f6sa komplexa teknikutmaningar som g\u00f6r verklig skillnad i m\u00e4nniskor liv!\nJust nu finns stora m\u00f6jligheter att direkt involveras i sp\u00e4nnande uppdrag, antingen p\u00e5 plats hos v\u00e5ra kunder eller in-house p\u00e5 i3tex kontor vid Klippan i G\u00f6teborg.\n\nF\u00f6rutom din erfarenhet och intresse f\u00f6r kod tror vi att du \u00e4r kreativ, kommunikativ och har ett \u00f6ga f\u00f6r detaljer. D\u00e5 vi jobbar med medicintekniska produkter och l\u00f6sningar \u00e4r dokumentation och regelefterlevnad viktiga delar f\u00f6r att s\u00e4kerst\u00e4lla dess kvalitet i alla led. D\u00e4rmed \u00e4r ett visst m\u00e5tt av t\u00e5lamod en klar f\u00f6rdel. \u2b50\n\nOM OSS\n\ni3tex \u00e4r ett visions- och v\u00e4rderingsstyrt tekniskt konsultbolag inom produktutveckling och tillsammans med v\u00e5ra kunder utvecklar vi framtidens produkter f\u00f6r en b\u00e4ttre v\u00e4rld. Vi tror p\u00e5 en stark f\u00f6retagskultur, att hj\u00e4lpa varandra att lyckas och att ha roligt tillsammans! Idag \u00e4r vi 170 medarbetare f\u00f6rdelat p\u00e5 6 kontor runtom i Sverige. V\u00e5ra kunder \u00e5terfinns inom Automotive, Medical Technology, IT & Digital Solutions, Aerospace och Industry. De tre i:en i i3tex st\u00e5r for Innovate, Implement, Improve!\n\nVill du st\u00e4lla fr\u00e5gor om tj\u00e4nsten eller om oss som f\u00f6retag kan du kontakta aff\u00e4rs- och medarbetaransvarig FIRSTNAME LASTNAME och har du fackliga fr\u00e5gor kan du kontakta n\u00e5gon av v\u00e5ra fackliga representanter via v\u00e4xeln  TELEPHONENO .\n\nVi ser fram emot din ans\u00f6kan!\n\nKontakt\n\nFIRSTNAME LASTNAME,  TELEPHONENO ", "publiceringsdatum": "2021-03-09 13:52:03", "sistaPubliceringsdatum": "2021-04-11 23:59:59", "sistaAnsokningsdatum": "2021-04-11 23:59:59", "avpublicerad": false, "antalPlatser": 1, "villkorsbeskrivning": "Heltid\r\nAnst\u00e4llningstid enligt \u00f6verenskommelse", "anstallningTyp": {"varde": "PFZr_Syz_cUq", "namn": "Vanlig anst\u00e4llning"}, "varaktighetTyp": {"varde": "a7uU_j21_mkL", "namn": "Tillsvidare"}, "arbetstidTyp": {"varde": "6YE1_gAC_R2G", "namn": "Heltid"}, "lonTyp": {"varde": "oG8G_9cW_nRf", "namn": "Fast m\u00e5nads- vecko- eller timl\u00f6n"}, "lonebeskrivning": "L\u00f6n enligt \u00f6verenskommelse", "organisationsnummer": "5565764668", "arbetsgivareId": "10813567", "arbetsgivareNamn": "I3Tex AB", "arbetsplatsId": "0", "arbetsplatsNamn": "i3tex", "ansokningssattWebbadress": "https://i3tex.teamtailor.com/jobs/1102531-software-developer-medtech?promotion=215621-arbetsformedlingen", "ansokningssattViaAF": false, "ejKravSvenskaEngelska": false, "inkluderande": false, "yrkesroll": {"varde": "rQds_YGd_quU", "namn": "Mjukvaruutvecklare"}, "ingenErfarenhetKravs": false, "yrkeserfarenheter": [{"varde": "rQds_YGd_quU", "namn": "Mjukvaruutvecklare", "vikt": 10, "erfarenhetsniva": {"varde": "yrAe_Fzi_E6u", "namn": "Mindre \u00e4n 1 \u00e5rs erfarenhet"}}], "tillgangTillEgenBil": false, "besoksadress": {"gatuadress": "Klippan 1A, G\u00f6teborg", "postnr": null, "postort": null, "land": null}, "postadress": {"gatuadress": "Klippan 1A", "postnr": "41451", "postort": "G\u00f6teborg", "land": "SE"}, "ansokningsadress": {"gatuadress": "Klippan 1A, G\u00f6teborg", "postnr": null, "postort": null, "land": null, "mottagare": null}, "uppdateradTid": 1615294323839, "arbetsplatsadress": {"gatuadress": null, "postnr": null, "postort": null, "land": {"varde": "i46j_HmG_v64", "namn": "Sverige"}, "lan": {"varde": "zdoY_6u5_Krt", "namn": "V\u00e4stra G\u00f6talands l\u00e4n"}, "kommun": {"varde": "PVZL_BQT_XtL", "namn": "G\u00f6teborg"}, "latitud": "57.70887", "longitud": "11.97456", "koordinatPrecision": "KOMMUN"}, "kontaktpersoner": [{"fornamn": "Testy", "efternamn": "Testsson", "befattning": null, "telefonnummer": "+01011122233", "epost": "test@jobtechdev.se", "fackligRepresentant": false, "beskrivning": "blabla"}], "informationAnsokningssatt": null, "telefonnummer": null, "ansokningssattEpost": null}