{"annonsId": 24607903, "kallaTyp": "VIA_PLATSBANKEN_DXA", "version": "1.0", "externtAnnonsId": "46-556115-5838-1062427-1", "annonsrubrik": "Senior Process Engineer", "annonstext": "Are you a production/process engineer who wants to take the next step in your career? At Profoto, you will be working in a fast-growing company that provides world-class products to the world\u2019s best image creators. Would you like to work in an international environment with world leading products, this position is for you!\n\nWhat we are looking for\nWe are looking for a Senior Process Engineer to our headquarter in Sundbyberg. You will be part of the Operations & Quality Team and the department responsible of Quality and Cost of our product. The production is fully outsourced, which will give you the opportunity to work with international sub-suppliers. You will lead the industrialization of new products as part of the New Product Development Team and work closely to our suppliers and ensure that the delivery is in line with Profoto expectations.\n\nKey responsibilities\nAs the leading brand on our market, Profoto always strives to deliver world-class quality as it is central to our brand promise. You will be fully responsible for and work with both operational and strategic activities. Other responsibilities:\n\n- Lead the industrialization of the new products all the way from product idea to volume production\n- Secure COGS and Quality of the products in production\n\nThis will be reached by:\n\n- Leading internal and external project resources as well as our European and Asian partners resources to ensure Profoto\u2019s process is followed\n- Secure and lead the implementation of the Engineering Change Order in production\n- Perform regular process audits at the supplier facilities\n- Contribute to the improvement of the industrialization & engineering change order processes\n- Support KPI development, follow-up and reporting on cost, yield and production capacity\n- Lead/participate in Product Claim analysis before potential re-engineering of existing products Lead/participate in Root Cause Analysis activities for the chosen identified failure.\n\nRequirements\nWe expect that you have a good understanding of manufacturing processes and continuous improvement methods, as well as\n\n- 3-5 years relevant experience within a manufacturing/development organization, preferably including some electronics and mechanics assembly.\n- Experienced in project management, stakeholder management and communication\n\n- Proven previous experience within production engineering management\n- Documented knowledge of manufacturing and/or quality management\n- Experienced in practical problem solving methodologies (e.g. 8D, A3\u2026)\n\n- Knowledge of Lean, Six Sigma or similar improvement frameworks\n- Fluent in English, spoken and written.\n- Relevant Master of Science degree or equivalent\n- Ability to travel: 30-50 days/year\n\nYour profile\nYou enjoy working in a dynamic, result driven and innovative environment. Moreover, you are skilled in influencing others to get things done. You can work either on process development level or hands-on when required. As we have operations in different parts of the world we want you to be open minded and handle cross functional activities and cultures specificities. You are a team player who want to develop your project management, stakeholder management and problem-solving skills.\n\nWant to join Profoto - The Light Shaping Company?\nIf you feel you have what it takes to become the next Senior Process engineer, please send an application with your CV, personal letter, and education records from university and high school. If you have any questions regarding role, please contact FIRSTNAME LASTNAME, Production Manager,  TELEPHONENO .\n\nLast day to apply is 8th April 2021. Interviews will take place on a continuous basis, so apply today!\n\nWhat we offer\nInnovation has secured our position as the leading choice for the world's best photographers. So, our culture is creative, entrepreneurial, forward thinking and agile. That's why we're looking for the very best and the very brightest to help make us better. Talented and driven people who are keen to enter a growing and fast-paced environment where responsibility is given early.\n\nWe are committed to growth and we want our people to grow with us. To achieve this we offer an ambitious, high quality and demanding culture where we value to have fun together as we build a world class company with a premium brand. We strongly believe and therefore offer our employees freedom and trust, coaching leadership and strong individual development. This is massively important for us because ultimately - your success is our success.", "annonstextFormaterad": "Are you a production/process engineer who wants to take the next step in your career? At Profoto, you will be working in a fast-growing company that provides world-class products to the world\u2019s best image creators. Would you like to work in an international environment with world leading products, this position is for you!\n\nWhat we are looking for\nWe are looking for a Senior Process Engineer to our headquarter in Sundbyberg. You will be part of the Operations & Quality Team and the department responsible of Quality and Cost of our product. The production is fully outsourced, which will give you the opportunity to work with international sub-suppliers. You will lead the industrialization of new products as part of the New Product Development Team and work closely to our suppliers and ensure that the delivery is in line with Profoto expectations.\n\nKey responsibilities\nAs the leading brand on our market, Profoto always strives to deliver world-class quality as it is central to our brand promise. You will be fully responsible for and work with both operational and strategic activities. Other responsibilities:\n\n- Lead the industrialization of the new products all the way from product idea to volume production\n- Secure COGS and Quality of the products in production\n\n\nThis will be reached by:\n\n- Leading internal and external project resources as well as our European and Asian partners resources to ensure Profoto\u2019s process is followed\n- Secure and lead the implementation of the Engineering Change Order in production\n- Perform regular process audits at the supplier facilities\n- Contribute to the improvement of the industrialization & engineering change order processes\n- Support KPI development, follow-up and reporting on cost, yield and production capacity\n- Lead/participate in Product Claim analysis before potential re-engineering of existing products Lead/participate in Root Cause Analysis activities for the chosen identified failure.\n\n\nRequirements\nWe expect that you have a good understanding of manufacturing processes and continuous improvement methods, as well as\n\n- 3-5 years relevant experience within a manufacturing/development organization, preferably including some electronics and mechanics assembly.\n- Experienced in project management, stakeholder management and communication\n\n\n- Proven previous experience within production engineering management\n- Documented knowledge of manufacturing and/or quality management\n- Experienced in practical problem solving methodologies (e.g. 8D, A3\u2026)\n\n\n- Knowledge of Lean, Six Sigma or similar improvement frameworks\n- Fluent in English, spoken and written.\n- Relevant Master of Science degree or equivalent\n- Ability to travel: 30-50 days/year\n\n\nYour profile\nYou enjoy working in a dynamic, result driven and innovative environment. Moreover, you are skilled in influencing others to get things done. You can work either on process development level or hands-on when required. As we have operations in different parts of the world we want you to be open minded and handle cross functional activities and cultures specificities. You are a team player who want to develop your project management, stakeholder management and problem-solving skills.\n\nWant to join Profoto - The Light Shaping Company?\nIf you feel you have what it takes to become the next Senior Process engineer, please send an application with your CV, personal letter, and education records from university and high school. If you have any questions regarding role, please contact FIRSTNAME LASTNAME, Production Manager,  TELEPHONENO .\n\nLast day to apply is 8th April 2021. Interviews will take place on a continuous basis, so apply today!\n\nWhat we offer\nInnovation has secured our position as the leading choice for the world's best photographers. So, our culture is creative, entrepreneurial, forward thinking and agile. That's why we're looking for the very best and the very brightest to help make us better. Talented and driven people who are keen to enter a growing and fast-paced environment where responsibility is given early.\n\nWe are committed to growth and we want our people to grow with us. To achieve this we offer an ambitious, high quality and demanding culture where we value to have fun together as we build a world class company with a premium brand. We strongly believe and therefore offer our employees freedom and trust, coaching leadership and strong individual development. This is massively important for us because ultimately - your success is our success.", "publiceringsdatum": "2021-03-10 06:48:02", "sistaPubliceringsdatum": "2021-08-27 23:59:59", "sistaAnsokningsdatum": "2021-08-27 23:59:59", "avpublicerad": false, "antalPlatser": 1, "webbadress": "https://www.profoto.com", "villkorsbeskrivning": "Heltid\r\nAnst\u00e4llningstid enligt \u00f6verenskommelse", "anstallningTyp": {"varde": "PFZr_Syz_cUq", "namn": "Vanlig anst\u00e4llning"}, "varaktighetTyp": {"varde": "a7uU_j21_mkL", "namn": "Tillsvidare"}, "arbetstidTyp": {"varde": "6YE1_gAC_R2G", "namn": "Heltid"}, "lonTyp": {"varde": "oG8G_9cW_nRf", "namn": "Fast m\u00e5nads- vecko- eller timl\u00f6n"}, "lonebeskrivning": "L\u00f6n enligt \u00f6verenskommelse", "organisationsnummer": "5561155838", "arbetsgivareId": "10802690", "arbetsgivareNamn": "Profoto AB", "arbetsplatsId": "0", "arbetsplatsNamn": "Profoto", "ansokningssattWebbadress": "https://career.profoto.com/jobs/1062427-senior-process-engineer?promotion=215790-arbetsformedlingen", "ansokningssattViaAF": false, "ejKravSvenskaEngelska": false, "inkluderande": false, "yrkesroll": {"varde": "pJKs_jnz_qCp", "namn": "Arbetsledare, tillverkning elektroniska prod."}, "ingenErfarenhetKravs": false, "yrkeserfarenheter": [{"varde": "pJKs_jnz_qCp", "namn": "Arbetsledare, tillverkning elektroniska prod.", "vikt": 10, "erfarenhetsniva": {"varde": "yrAe_Fzi_E6u", "namn": "Mindre \u00e4n 1 \u00e5rs erfarenhet"}}], "tillgangTillEgenBil": false, "besoksadress": {"gatuadress": "Profoto AB, Sundbyberg", "postnr": null, "postort": null, "land": null}, "postadress": {"gatuadress": "Profoto AB", "postnr": "17265", "postort": "Sundbyberg", "land": "SE"}, "ansokningsadress": {"gatuadress": "Profoto AB, Sundbyberg", "postnr": null, "postort": null, "land": null, "mottagare": null}, "uppdateradTid": 1615355282898, "arbetsplatsadress": {"gatuadress": null, "postnr": null, "postort": null, "land": {"varde": "i46j_HmG_v64", "namn": "Sverige"}, "lan": {"varde": "CifL_Rzy_Mku", "namn": "Stockholms l\u00e4n"}, "kommun": {"varde": "AvNB_uwa_6n6", "namn": "Stockholm"}, "latitud": "59.329323", "longitud": "18.06858", "koordinatPrecision": "KOMMUN"}, "kontaktpersoner": [{"fornamn": "Testy", "efternamn": "Testsson", "befattning": null, "telefonnummer": "+01011122233", "epost": "test@jobtechdev.se", "fackligRepresentant": false, "beskrivning": "blabla"}], "informationAnsokningssatt": null, "telefonnummer": null, "ansokningssattEpost": null}