{"annonsId": 24615943, "kallaTyp": "VIA_PLATSBANKEN_DXA", "version": "1.0", "externtAnnonsId": "46-556986-8101-187684604b2cbc94da8", "annonsrubrik": "Embedded Developers with C/C++", "annonstext": "If you thrive to work with Software development that are specific, this is the job for you. We are now looking for Embedded Developers with C/C++ by profession to take a challenge for an international client in the Automotive industry.\n\nJob responsibilities:\n\nYou should have relevant experience in:\n-C and C++ from real time systems.\n-Embedded experience from LINUX drivers and git, habit.\n-Building systems like Cmake, Jenkins, Xilinx platforms.\n-Buildroot and yocto (to build Linux hw from scratch) writing tests.\n-Agile, Scrum habit.\n-Network and Socket.\n\nPersonal competence:\n\nStrong English communication skills\nTaking responsibility and working in a changing environment.\nYou are a strong team player but can also act independently and take initiatives on your own. \n\nAbout the role:\n\nIn this role you will be working on-site with our client but at the same time part of our exciting NXT-team and new assignment possibilities. We want to inspire and motivate you on your journey towards your aspirations.\n\nWe offer:\n\nWe help you to find new exciting assignments and assign an exclusive Agent who represent you in the process.\n\nHow to apply:\n\nIf you are interested to become our next consultant, take the first step to move forward. We interview candidates continuously so apply already today! We handle both you and your information confidentially and we begin with a first contact and then you will get to know more about NXT Interim and how we can help you. Welcome with your application! If you thrive to work with Software development that are specific, this is the job for you. We are now looking for Embedded Developers with C/C++ by profession to take a challenge for an international client in the Automotive industry.\n\nJob responsibilities:\n\nYou should have relevant experience in:\n-C and C++ from real time systems.\n-Embedded experience from LINUX drivers and git, habit.\n-Building systems like Cmake, Jenkins, Xilinx platforms.\n-Buildroot and yocto (to build Linux hw from scratch) writing tests.\n-Agile, Scrum habit.\n-Network and Socket.\n\nPersonal competence:\n\nStrong English communication skills\nTaking responsibility and working in a changing environment.\nYou are a strong team player but can also act independently and take initiatives on your own. \n\nAbout the role:\n\nIn this role you will be working on-site with our client but at the same time part of our exciting NXT-team and new assignment possibilities. We want to inspire and motivate you on your journey towards your aspirations.\n\nWe offer:\n\nWe help you to find new exciting assignments and assign an exclusive Agent who represent you in the process.\n\nHow to apply:\n\nIf you are interested to become our next consultant, take the first step to move forward. We interview candidates continuously so apply already today! We handle both you and your information confidentially and we begin with a first contact and then you will get to know more about NXT Interim and how we can help you. Welcome with your application! NXT Interim och NXT Rekrytering \u00e4r ett innovativt f\u00f6retag som erbjuder tj\u00e4nster och en paketering som de traditionella f\u00f6retagen inte erbjuder idag.\n\nEfter m\u00e5nga \u00e5r i branschen och f\u00f6rkovrande i unders\u00f6kningar och forskning har vi paketerat olika l\u00f6sningar f\u00f6r att tillgodose allas behov.\n\nVi har i princip v\u00e4nt p\u00e5 alla processer f\u00f6r att alltid tillgodose v\u00e5ra kunder och konsulters behov.\nVi ser \u00e4ven till att erbjuda v\u00e5ra konsulter alla de extraverktyg som kr\u00e4vs f\u00f6r att lyckas.\nFramtidens konsulter har en \u00f6nskan om st\u00f6rre flexibilitet och ett st\u00f6rre engagemang i m\u00e5nga fr\u00e5gor, vi tillgodoser dessa behov genom NXT Interim.\nDetta tillsammans med den digitalisering som st\u00e4ndigt p\u00e5g\u00e5r g\u00f6r att vi snabbt kan tillgodose v\u00e5ra kunder och konsulters behov.\nVi har gjort 3 olika paketeringar f\u00f6r v\u00e5ra konsulter som hj\u00e4lper dom att lyckas i sitt   f\u00f6retagande och kan fokusera p\u00e5 det som dom \u00e4r b\u00e4st p\u00e5, dvs att vara specialister.\nVi har idag 3000 unika kontakter inom v\u00e5r nisch. Genom agilt och proaktivt arbete blir vi den naturliga agenten f\u00f6r b\u00e5de f\u00f6retag och f\u00f6retagare.\n\n\u201dV\u00e5rt m\u00e5l \u00e4r att g\u00e5 fr\u00e5n att vara en innovativ utmanare i branschen till att vara det f\u00f6retag i branschen som alla vill sl\u00e5\u201d", "annonstextFormaterad": "<div>If you thrive to work with Software development that are specific, this is the job for you.\u00a0We are now looking for Embedded Developers with C/C++ by profession to take a challenge for an international client in the Automotive industry.<br><br>Job responsibilities:<br><br>You should have relevant experience in:<br>-C and C++ from real time systems.<br>-Embedded experience from LINUX drivers and git, habit.<br>-Building systems like Cmake, Jenkins, Xilinx platforms.<br>-Buildroot and yocto (to build Linux hw from scratch) writing tests.<br>-Agile, Scrum habit.<br>-Network and Socket.<br><br>Personal competence:<br><br>Strong English communication skills<br>Taking responsibility and working in a changing environment.<br>You are a strong team player but can also act independently and take initiatives on your own.\u00a0<br><br>About the role:<br><br>In this role you will be working on-site with our client but at the same time part of our exciting NXT-team and new assignment possibilities. We want to inspire and motivate you on your journey towards your aspirations.<br><br>We offer:<br><br>We help you to find new exciting assignments and assign an exclusive Agent who represent you in the process.<br><br>How to apply:<br><br>If you are interested to become our next consultant, take the first step to move forward. We interview candidates continuously so apply already today! We handle both you and your information confidentially and we begin with a first contact and then you will get to know more about NXT Interim and how we can help you.\u00a0Welcome with your application!<div><div>\u00a0<div>If you thrive to work with Software development that are specific, this is the job for you.\u00a0We are now looking for Embedded Developers with C/C++ by profession to take a challenge for an international client in the Automotive industry.<br><br>Job responsibilities:<br><br>You should have relevant experience in:<br>-C and C++ from real time systems.<br>-Embedded experience from LINUX drivers and git, habit.<br>-Building systems like Cmake, Jenkins, Xilinx platforms.<br>-Buildroot and yocto (to build Linux hw from scratch) writing tests.<br>-Agile, Scrum habit.<br>-Network and Socket.<br><br>Personal competence:<br><br>Strong English communication skills<br>Taking responsibility and working in a changing environment.<br>You are a strong team player but can also act independently and take initiatives on your own.\u00a0<br><br>About the role:<br><br>In this role you will be working on-site with our client but at the same time part of our exciting NXT-team and new assignment possibilities. We want to inspire and motivate you on your journey towards your aspirations.<br><br>We offer:<br><br>We help you to find new exciting assignments and assign an exclusive Agent who represent you in the process.<br><br>How to apply:<br><br>If you are interested to become our next consultant, take the first step to move forward. We interview candidates continuously so apply already today! We handle both you and your information confidentially and we begin with a first contact and then you will get to know more about NXT Interim and how we can help you.\u00a0Welcome with your application!<div><div>\u00a0</div></div></div><em>NXT Interim och NXT Rekrytering \u00e4r ett innovativt f\u00f6retag som erbjuder tj\u00e4nster och en paketering som de traditionella f\u00f6retagen inte erbjuder idag.<br><br>Efter m\u00e5nga \u00e5r i branschen och f\u00f6rkovrande i unders\u00f6kningar och forskning har vi paketerat olika l\u00f6sningar f\u00f6r att tillgodose allas behov.<br><br>Vi har i princip v\u00e4nt p\u00e5 alla processer f\u00f6r att alltid tillgodose v\u00e5ra kunder och konsulters behov.<br>Vi ser \u00e4ven till att erbjuda v\u00e5ra konsulter alla de extraverktyg som kr\u00e4vs f\u00f6r att lyckas.<br>Framtidens konsulter har en \u00f6nskan om st\u00f6rre flexibilitet och ett st\u00f6rre engagemang i m\u00e5nga fr\u00e5gor, vi tillgodoser dessa behov genom NXT Interim.<br>Detta tillsammans med den digitalisering som st\u00e4ndigt p\u00e5g\u00e5r g\u00f6r att vi snabbt kan tillgodose v\u00e5ra kunder och konsulters behov.<br>Vi har gjort 3 olika paketeringar f\u00f6r v\u00e5ra konsulter som hj\u00e4lper dom att lyckas i sitt\u00a0\u00a0 f\u00f6retagande och kan fokusera p\u00e5 det som dom \u00e4r b\u00e4st p\u00e5, dvs att vara specialister.<br>Vi har idag 3000 unika kontakter inom v\u00e5r nisch. Genom agilt och proaktivt arbete blir vi den naturliga agenten f\u00f6r b\u00e5de f\u00f6retag och f\u00f6retagare.<br><br>\u201dV\u00e5rt m\u00e5l \u00e4r att g\u00e5 fr\u00e5n att vara en innovativ utmanare i branschen till att vara det f\u00f6retag i branschen som alla vill sl\u00e5\u201d</em><br><br>\u00a0</div></div></div>", "publiceringsdatum": "2021-03-12 09:56:35", "sistaPubliceringsdatum": "2021-04-09 23:59:59", "sistaAnsokningsdatum": "2021-04-09 23:59:59", "avpublicerad": false, "antalPlatser": 1, "anstallningTyp": {"varde": "PFZr_Syz_cUq", "namn": "Vanlig anst\u00e4llning"}, "varaktighetTyp": {"varde": "a7uU_j21_mkL", "namn": "Tillsvidare"}, "arbetstidTyp": {"varde": "6YE1_gAC_R2G", "namn": "Heltid"}, "lonTyp": {"varde": "oG8G_9cW_nRf", "namn": "Fast m\u00e5nads- vecko- eller timl\u00f6n"}, "organisationsnummer": "5569868101", "arbetsgivareId": "21134602", "arbetsgivareNamn": "NXT Interim AB", "arbetsplatsId": "0", "arbetsplatsNamn": "NXT Rekrytering", "ansokningssattWebbadress": "https://apply.recman.no/job_post.php?id=187684&path=ams", "ansokningssattViaAF": false, "ejKravSvenskaEngelska": false, "inkluderande": false, "yrkesroll": {"varde": "fg7B_yov_smw", "namn": "Systemutvecklare/Programmerare"}, "ingenErfarenhetKravs": false, "yrkeserfarenheter": [{"varde": "fg7B_yov_smw", "namn": "Systemutvecklare/Programmerare", "vikt": 10, "erfarenhetsniva": {"varde": "yrAe_Fzi_E6u", "namn": "Mindre \u00e4n 1 \u00e5rs erfarenhet"}}], "tillgangTillEgenBil": false, "besoksadress": {"gatuadress": "Industrigatan 5", "postnr": null, "postort": null, "land": null}, "postadress": {"gatuadress": "Industrigatan 5", "postnr": "58277", "postort": "Link\u00f6ping", "land": "SE"}, "ansokningsadress": {"gatuadress": "Industrigatan 5", "postnr": null, "postort": null, "land": null, "mottagare": null}, "uppdateradTid": 1615539395367, "arbetsplatsadress": {"gatuadress": null, "postnr": null, "postort": null, "land": {"varde": "i46j_HmG_v64", "namn": "Sverige"}, "lan": {"varde": "oLT3_Q9p_3nn", "namn": "\u00d6sterg\u00f6tlands l\u00e4n"}, "kommun": {"varde": "bm2x_1mr_Qhx", "namn": "Link\u00f6ping"}, "latitud": "58.41081", "longitud": "15.621373", "koordinatPrecision": "KOMMUN"}, "kontaktpersoner": [{"fornamn": "Testy", "efternamn": "Testsson", "befattning": null, "telefonnummer": "+01011122233", "epost": "test@jobtechdev.se", "fackligRepresentant": false, "beskrivning": "blabla"}], "informationAnsokningssatt": null, "telefonnummer": null, "ansokningssattEpost": null}