{"annonsId": 24625106, "kallaTyp": "VIA_PLATSBANKEN_DXA", "version": "1.0", "externtAnnonsId": "46-556601-9823-928469-47", "annonsrubrik": "Allm\u00e4nspecialist till Achima Care Sala v\u00e5rdcentral", "annonstext": "Nu s\u00f6ker vi l\u00e4kare till Achima Care Sala v\u00e5rdcentral!\n\nAchima Care i Sala v\u00e4xer och ut\u00f6kar d\u00e4r med v\u00e5r l\u00e4kargrupp. Vi s\u00f6ker dig som \u00e4r specialist i allm\u00e4nmedicin. I rollen ing\u00e5r kliniskt arbete d\u00e4r kvalit\u00e9 och patients\u00e4kerhet i den medicinska behandlingen st\u00e5r i fokus.\n\nUnikt med detta jobb \u00e4r:\n\nH\u00f6g dos av arbetsgl\u00e4dje och stora m\u00f6jligheter att p\u00e5verka arbetsinneh\u00e5llet\nDu jobbar med egen lista av patienter f\u00f6r h\u00f6g kontinuitet\nVi jobbar n\u00e4ra andra yrkeskategorier och samverkar runt patienten f\u00f6r b\u00e4sta omh\u00e4ndertagande\nStor frihet att komma med f\u00f6rslag\n\nDu \u00e4r flexibel, trygg och kan arbeta sj\u00e4lvst\u00e4ndigt. Du trivs med att ta initiativ och har en god samarbetsf\u00f6rm\u00e5ga. Mot patienter \u00e4r du \u00e4r lyh\u00f6rd och l\u00f6sningsfokuserad d\u00e4r fokus alltid ligger p\u00e5 patientens b\u00e4sta.\n\nVi kan erbjuda dig ett utvecklande jobb p\u00e5 en v\u00e5rdcentral som s\u00e4tter kvalitet och patients\u00e4kerhet som h\u00f6gsta prioritet. Sala v\u00e5rdcentral har en stark och positiv f\u00f6retagskultur d\u00e4r vi ser till att ha roligt tillsammans. Du kommer att ing\u00e5 i ett team om cirka 30 medarbetare d\u00e4r vi tillsammans tar hand om cirka 9 300 listade patienter.\n\nAnst\u00e4llningsvillkor\n- Tillsvidareanst\u00e4llning, heltid\n- Arbetstid, dagtid vardagar\n- Tilltr\u00e4de enligt \u00f6verenskommelse\n\nOm Achima\nAchimas uppdrag \u00e4r att arbeta f\u00f6rebyggande med h\u00e4lsa och erbjuda en l\u00e4ttillg\u00e4nglig och trygg sjukv\u00e5rd. Det har vi haft f\u00f6rm\u00e5nen att g\u00f6ra sedan 2004. Achima best\u00e5r idag av 10 v\u00e5rdcentraler och rehabenheter runt om i landet. Achima lednings utg\u00e5r ifr\u00e5n huvudkontoret i Karlskrona som best\u00e5r av st\u00f6dfunktioner s\u00e5 som HR, Ekonomi, Ink\u00f6p, Marknad och IT.\n\nV\u00e5r arbetsfilosofi kallar vi The Achima Way vilket inneb\u00e4r att vi f\u00f6rb\u00e4ttrar v\u00e5rdsverige. N\u00e4r man arbetar enligt The Achima Way tar man ansvar f\u00f6r att arbeta enligt f\u00f6rh\u00e5llningss\u00e4ttet som vi kallar Achima-ansvaret.\n\nL\u00e4s g\u00e4rna mer p\u00e5 v\u00e5r hemsida: https://www.achima.se/om-oss/the-achima-way-achima-ansvaret/\n\nF\u00f6r mer information h\u00f6r av dig till verksamhetschef Agnes Tejlerdal p\u00e5  EMAIL \n\nUrval och rekrytering sker l\u00f6pande. Tack f\u00f6r att du ans\u00f6ker via l\u00e4nken i annonsen.\n\nVi undanber oss alla erbjudande om annonsering och rekryteringshj\u00e4lp i samband med denna annons.", "annonstextFormaterad": "Nu s\u00f6ker vi l\u00e4kare till Achima Care Sala v\u00e5rdcentral!\n\nAchima Care i Sala v\u00e4xer och ut\u00f6kar d\u00e4r med v\u00e5r l\u00e4kargrupp. Vi s\u00f6ker dig som \u00e4r specialist i allm\u00e4nmedicin. I rollen ing\u00e5r kliniskt arbete d\u00e4r kvalit\u00e9 och patients\u00e4kerhet i den medicinska behandlingen st\u00e5r i fokus.\n\nUnikt med detta jobb \u00e4r:\n\nH\u00f6g dos av arbetsgl\u00e4dje och stora m\u00f6jligheter att p\u00e5verka arbetsinneh\u00e5llet\nDu jobbar med egen lista av patienter f\u00f6r h\u00f6g kontinuitet\nVi jobbar n\u00e4ra andra yrkeskategorier och samverkar runt patienten f\u00f6r b\u00e4sta omh\u00e4ndertagande\nStor frihet att komma med f\u00f6rslag\n\n\nDu \u00e4r flexibel, trygg och kan arbeta sj\u00e4lvst\u00e4ndigt. Du trivs med att ta initiativ och har en god samarbetsf\u00f6rm\u00e5ga. Mot patienter \u00e4r du \u00e4r lyh\u00f6rd och l\u00f6sningsfokuserad d\u00e4r fokus alltid ligger p\u00e5 patientens b\u00e4sta.\n\nVi kan erbjuda dig ett utvecklande jobb p\u00e5 en v\u00e5rdcentral som s\u00e4tter kvalitet och patients\u00e4kerhet som h\u00f6gsta prioritet. Sala v\u00e5rdcentral har en stark och positiv f\u00f6retagskultur d\u00e4r vi ser till att ha roligt tillsammans. Du kommer att ing\u00e5 i ett team om cirka 30 medarbetare d\u00e4r vi tillsammans tar hand om cirka 9 300 listade patienter.\n\nAnst\u00e4llningsvillkor\n- Tillsvidareanst\u00e4llning, heltid\n- Arbetstid, dagtid vardagar\n- Tilltr\u00e4de enligt \u00f6verenskommelse\n\nOm Achima\nAchimas uppdrag \u00e4r att arbeta f\u00f6rebyggande med h\u00e4lsa och erbjuda en l\u00e4ttillg\u00e4nglig och trygg sjukv\u00e5rd. Det har vi haft f\u00f6rm\u00e5nen att g\u00f6ra sedan 2004. Achima best\u00e5r idag av 10 v\u00e5rdcentraler och rehabenheter runt om i landet. Achima lednings utg\u00e5r ifr\u00e5n huvudkontoret i Karlskrona som best\u00e5r av st\u00f6dfunktioner s\u00e5 som HR, Ekonomi, Ink\u00f6p, Marknad och IT.\n\nV\u00e5r arbetsfilosofi kallar vi The Achima Way vilket inneb\u00e4r att vi f\u00f6rb\u00e4ttrar v\u00e5rdsverige. N\u00e4r man arbetar enligt The Achima Way tar man ansvar f\u00f6r att arbeta enligt f\u00f6rh\u00e5llningss\u00e4ttet som vi kallar Achima-ansvaret.\n\nL\u00e4s g\u00e4rna mer p\u00e5 v\u00e5r hemsida: https://www.achima.se/om-oss/the-achima-way-achima-ansvaret/\n\nF\u00f6r mer information h\u00f6r av dig till verksamhetschef Agnes Tejlerdal p\u00e5  EMAIL \n\nUrval och rekrytering sker l\u00f6pande. Tack f\u00f6r att du ans\u00f6ker via l\u00e4nken i annonsen.\n\nVi undanber oss alla erbjudande om annonsering och rekryteringshj\u00e4lp i samband med denna annons.", "publiceringsdatum": "2021-03-16 11:36:47", "sistaPubliceringsdatum": "2021-03-31 23:59:59", "sistaAnsokningsdatum": "2021-03-31 23:59:59", "avpublicerad": false, "antalPlatser": 1, "webbadress": "http://www.achima.se/", "villkorsbeskrivning": "Heltid\r\nAnst\u00e4llningstid enligt \u00f6verenskommelse", "anstallningTyp": {"varde": "PFZr_Syz_cUq", "namn": "Vanlig anst\u00e4llning"}, "varaktighetTyp": {"varde": "a7uU_j21_mkL", "namn": "Tillsvidare"}, "arbetstidTyp": {"varde": "6YE1_gAC_R2G", "namn": "Heltid"}, "lonTyp": {"varde": "oG8G_9cW_nRf", "namn": "Fast m\u00e5nads- vecko- eller timl\u00f6n"}, "lonebeskrivning": "L\u00f6n enligt \u00f6verenskommelse", "organisationsnummer": "5566019823", "arbetsgivareId": "10814816", "arbetsgivareNamn": "Achima Care AB", "arbetsplatsId": "0", "arbetsplatsNamn": "Achima Care", "ansokningssattWebbadress": "http://achima.teamtailor.com/jobs/928469-allmanspecialist-till-achima-care-sala-vardcentral?promotion=172432-arbetsformedlingen", "ansokningssattViaAF": false, "ejKravSvenskaEngelska": false, "inkluderande": false, "yrkesroll": {"varde": "oHyy_M2j_HUP", "namn": "Specialistl\u00e4kare"}, "ingenErfarenhetKravs": false, "yrkeserfarenheter": [{"varde": "oHyy_M2j_HUP", "namn": "Specialistl\u00e4kare", "vikt": 10, "erfarenhetsniva": {"varde": "yrAe_Fzi_E6u", "namn": "Mindre \u00e4n 1 \u00e5rs erfarenhet"}}], "tillgangTillEgenBil": false, "besoksadress": {"gatuadress": "K\u00e5lg\u00e5rdsgatan 7, Sala", "postnr": null, "postort": null, "land": null}, "postadress": {"gatuadress": "K\u00e5lg\u00e5rdsgatan 7", "postnr": "73331", "postort": "Sala", "land": "SE"}, "ansokningsadress": {"gatuadress": "K\u00e5lg\u00e5rdsgatan 7, Sala", "postnr": null, "postort": null, "land": null, "mottagare": null}, "uppdateradTid": 1615891007066, "arbetsplatsadress": {"gatuadress": null, "postnr": null, "postort": null, "land": {"varde": "i46j_HmG_v64", "namn": "Sverige"}, "lan": {"varde": "G6DV_fKE_Viz", "namn": "V\u00e4stmanlands l\u00e4n"}, "kommun": {"varde": "dAen_yTK_tqz", "namn": "Sala"}, "latitud": "59.92086", "longitud": "16.606327", "koordinatPrecision": "KOMMUN"}, "kontaktpersoner": [{"fornamn": "Testy", "efternamn": "Testsson", "befattning": null, "telefonnummer": "+01011122233", "epost": "test@jobtechdev.se", "fackligRepresentant": false, "beskrivning": "blabla"}], "informationAnsokningssatt": null, "telefonnummer": null, "ansokningssattEpost": null}