{"annonsId": 24620694, "kallaTyp": "VIA_PLATSBANKEN_DXA", "version": "1.0", "externtAnnonsId": "46-559048-8713-1063657-10", "annonsrubrik": "Kaminmont\u00f6r/murare - S\u00f6lvesborg - En tj\u00e4nst med bra h\u00f6jd f\u00f6r mycket v\u00e4rme!", "annonstext": "Om F\u00f6retaget\n\nF\u00f6retaget utf\u00f6r skorstensrenoveringar, b\u00e5de glidjutning och insattsr\u00f6r med garanti.\nSamt s\u00e4ljer och monterar alla typer av eldst\u00e4der och skorstenar.\nF\u00f6retaget \u00e4r leverant\u00f6r, mont\u00f6r och installat\u00f6r \u00e5t en butikskedja som finns p\u00e5 44 orter i Sverige.\n\nArbetsuppgifter\n\nArbetet \u00e4r i huvudsak kamin och skorstensmontage med en hel del murningsarbete. Det f\u00f6rekommer \u00e4ven en del byggarbeten samt en del fastighets relaterade arbeten.\nArbete p\u00e5 tak och h\u00f6gre h\u00f6jder \u00e4r st\u00e4ndigt f\u00f6rekommande, vi s\u00f6ker dig som inte \u00e4r r\u00e4dd f\u00f6r att ta i d\u00e5 arbetet innefattar en del fysiskt kr\u00e4vande moment.\nHos oss f\u00e5r du ett varierande arbete, d\u00e4r ena dagen \u00e4r inte den andra lik.\n\nPersonliga Egenskaper\n\nF\u00f6retaget s\u00f6ker en driven och noggrann mont\u00f6r p\u00e5 heltid, med positiv inst\u00e4llning.\nDu \u00e4r sj\u00e4lvg\u00e5ende och tar ansvar f\u00f6r dina uppgifter, \u00e4r strukturerad och kan arbeta b\u00e5de sj\u00e4lvst\u00e4ndigt och med andra.\n\nKrav\n\n- Erfarenhet av murning via utbildning eller erfarenhet\n- B- k\u00f6rkort\n- Kan uttrycka sig v\u00e4l i tal och skrift p\u00e5 svenska\n\nMeriter\n\n- Tidigare erfarenhet fr\u00e5n yrket\n\nVaraktighet och tilltr\u00e4de\n\nTj\u00e4nsten \u00e4r heltid med arbetstider mellan 07:00 -16:00,\nl\u00f6n och tilltr\u00e4de enligt \u00f6verenskommelse.\n\nVad har f\u00f6retaget att erbjuda\n\n- F\u00f6retaget \u00e4r en trygg och stabil arbetsplats med m\u00e5nga \u00e5rs erfarenhet\n- Starka och marknadsm\u00e4ssiga l\u00f6ner\n- Som anst\u00e4lld hos dem f\u00e5r man mycket frihet och man sk\u00f6ter sina egna jobb\n- Hos f\u00f6retaget finns det alltid jobb och vi har aldrig beh\u00f6vt avskeda n\u00e5gon.\u201d\n\nD\u00e5 urval kommer ske l\u00f6pande ser vi g\u00e4rna att du ans\u00f6ker s\u00e5 snart som m\u00f6jligt.\nV\u00e4lkommen med din ans\u00f6kan!\n\nVi tar ej emot ans\u00f6kningar via e-post p\u00e5 grund av den nya lagstiftningen GDPR. F\u00f6r att din ans\u00f6kan skall vara giltig, v\u00e4nligen registrera dig och ans\u00f6k via v\u00e5r annons eller hemsida.)\n\nOm oss\n\nConsultify \u00e4r f\u00f6retaget f\u00f6r unga talanger som vill komma direkt in p\u00e5 ett f\u00f6retag. D\u00e4r f\u00e5r du visa vad du g\u00e5r f\u00f6r mitt i hetluften, ist\u00e4llet f\u00f6r att bli ett namn p\u00e5 ett cv som bara hamnar p\u00e5 h\u00f6g. Vi \u00e4r ett service- och personalf\u00f6rmedlingsf\u00f6retag som brinner f\u00f6r att f\u00e5 ut ungdomar i givande och stimulerande jobbm\u00f6jligheter, bygga p\u00e5 cv:et, knyta kontakter och till slut f\u00e5 en fast anst\u00e4llning. Vi har huvudkontoret i Kalmar men finns \u00e4ven i V\u00e4xj\u00f6, Karlskrona och Halmstad.\n\nConsultify \u00e4r f\u00f6retaget som skapar riktiga jobb f\u00f6r Sveriges unga talanger!", "annonstextFormaterad": "Om F\u00f6retaget\n\nF\u00f6retaget utf\u00f6r skorstensrenoveringar, b\u00e5de glidjutning och insattsr\u00f6r med garanti.\nSamt s\u00e4ljer och monterar alla typer av eldst\u00e4der och skorstenar.\nF\u00f6retaget \u00e4r leverant\u00f6r, mont\u00f6r och installat\u00f6r \u00e5t en butikskedja som finns p\u00e5 44 orter i Sverige.\n\nArbetsuppgifter\n\nArbetet \u00e4r i huvudsak kamin och skorstensmontage med en hel del murningsarbete. Det f\u00f6rekommer \u00e4ven en del byggarbeten samt en del fastighets relaterade arbeten.\nArbete p\u00e5 tak och h\u00f6gre h\u00f6jder \u00e4r st\u00e4ndigt f\u00f6rekommande, vi s\u00f6ker dig som inte \u00e4r r\u00e4dd f\u00f6r att ta i d\u00e5 arbetet innefattar en del fysiskt kr\u00e4vande moment.\nHos oss f\u00e5r du ett varierande arbete, d\u00e4r ena dagen \u00e4r inte den andra lik.\n\nPersonliga Egenskaper\n\nF\u00f6retaget s\u00f6ker en driven och noggrann mont\u00f6r p\u00e5 heltid, med positiv inst\u00e4llning.\nDu \u00e4r sj\u00e4lvg\u00e5ende och tar ansvar f\u00f6r dina uppgifter, \u00e4r strukturerad och kan arbeta b\u00e5de sj\u00e4lvst\u00e4ndigt och med andra.\n\nKrav\n\n- Erfarenhet av murning via utbildning eller erfarenhet\n- B- k\u00f6rkort\n- Kan uttrycka sig v\u00e4l i tal och skrift p\u00e5 svenska\n\nMeriter\n\n- Tidigare erfarenhet fr\u00e5n yrket\n\nVaraktighet och tilltr\u00e4de\n\nTj\u00e4nsten \u00e4r heltid med arbetstider mellan 07:00 -16:00,\nl\u00f6n och tilltr\u00e4de enligt \u00f6verenskommelse.\n\nVad har f\u00f6retaget att erbjuda\n\n- F\u00f6retaget \u00e4r en trygg och stabil arbetsplats med m\u00e5nga \u00e5rs erfarenhet\n- Starka och marknadsm\u00e4ssiga l\u00f6ner\n- Som anst\u00e4lld hos dem f\u00e5r man mycket frihet och man sk\u00f6ter sina egna jobb\n- Hos f\u00f6retaget finns det alltid jobb och vi har aldrig beh\u00f6vt avskeda n\u00e5gon.\u201d\n\n\n\nD\u00e5 urval kommer ske l\u00f6pande ser vi g\u00e4rna att du ans\u00f6ker s\u00e5 snart som m\u00f6jligt.\nV\u00e4lkommen med din ans\u00f6kan!\n\nVi tar ej emot ans\u00f6kningar via e-post p\u00e5 grund av den nya lagstiftningen GDPR. F\u00f6r att din ans\u00f6kan skall vara giltig, v\u00e4nligen registrera dig och ans\u00f6k via v\u00e5r annons eller hemsida.)\n\n\n\n\n\nOm oss\n\nConsultify \u00e4r f\u00f6retaget f\u00f6r unga talanger som vill komma direkt in p\u00e5 ett f\u00f6retag. D\u00e4r f\u00e5r du visa vad du g\u00e5r f\u00f6r mitt i hetluften, ist\u00e4llet f\u00f6r att bli ett namn p\u00e5 ett cv som bara hamnar p\u00e5 h\u00f6g. Vi \u00e4r ett service- och personalf\u00f6rmedlingsf\u00f6retag som brinner f\u00f6r att f\u00e5 ut ungdomar i givande och stimulerande jobbm\u00f6jligheter, bygga p\u00e5 cv:et, knyta kontakter och till slut f\u00e5 en fast anst\u00e4llning. Vi har huvudkontoret i Kalmar men finns \u00e4ven i V\u00e4xj\u00f6, Karlskrona och Halmstad.\n\nConsultify \u00e4r f\u00f6retaget som skapar riktiga jobb f\u00f6r Sveriges unga talanger!", "publiceringsdatum": "2021-03-15 09:49:04", "sistaPubliceringsdatum": "2021-09-01 23:59:59", "sistaAnsokningsdatum": "2021-09-01 23:59:59", "avpublicerad": false, "antalPlatser": 1, "webbadress": "http://www.consultify.se", "villkorsbeskrivning": "Heltid\r\nAnst\u00e4llningstid enligt \u00f6verenskommelse", "anstallningTyp": {"varde": "PFZr_Syz_cUq", "namn": "Vanlig anst\u00e4llning"}, "varaktighetTyp": {"varde": "a7uU_j21_mkL", "namn": "Tillsvidare"}, "arbetstidTyp": {"varde": "6YE1_gAC_R2G", "namn": "Heltid"}, "lonTyp": {"varde": "oG8G_9cW_nRf", "namn": "Fast m\u00e5nads- vecko- eller timl\u00f6n"}, "lonebeskrivning": "L\u00f6n enligt \u00f6verenskommelse", "organisationsnummer": "5590488713", "arbetsgivareId": "21045947", "arbetsgivareNamn": "Consultify AB", "arbetsplatsId": "0", "arbetsplatsNamn": "Consultify AB", "ansokningssattWebbadress": "https://jobb.consultify.se/jobs/1063657-kaminmontor-murare-solvesborg-en-tjanst-med-bra-hojd-for-mycket-varme?promotion=205160-arbetsformedlingen", "ansokningssattViaAF": false, "ejKravSvenskaEngelska": false, "inkluderande": false, "yrkesroll": {"varde": "j3pm_WJX_Hty", "namn": "Murare, utan yrkesbevis"}, "ingenErfarenhetKravs": true, "tillgangTillEgenBil": false, "besoksadress": {"gatuadress": "Campus Gr\u00e4svik, Karlskrona", "postnr": null, "postort": null, "land": null}, "postadress": {"gatuadress": "Campus Gr\u00e4svik", "postnr": "37141", "postort": "Karlskrona", "land": "SE"}, "ansokningsadress": {"gatuadress": "Campus Gr\u00e4svik, Karlskrona", "postnr": null, "postort": null, "land": null, "mottagare": null}, "uppdateradTid": 1615798144527, "arbetsplatsadress": {"gatuadress": null, "postnr": null, "postort": null, "land": {"varde": "i46j_HmG_v64", "namn": "Sverige"}, "lan": {"varde": "DQZd_uYs_oKb", "namn": "Blekinge l\u00e4n"}, "kommun": {"varde": "EVPy_phD_8Vf", "namn": "S\u00f6lvesborg"}, "latitud": "56.05374", "longitud": "14.579688", "koordinatPrecision": "KOMMUN"}, "kontaktpersoner": [{"fornamn": "Testy", "efternamn": "Testsson", "befattning": null, "telefonnummer": "+01011122233", "epost": "test@jobtechdev.se", "fackligRepresentant": false, "beskrivning": "blabla"}], "informationAnsokningssatt": null, "telefonnummer": null, "ansokningssattEpost": null}