{"annonsId": 24624813, "kallaTyp": "VIA_ANNONSERA", "version": "1.0", "annonsrubrik": "Erfaren italiensk kock", "annonstext": "Vi \u00e4r en italiensk restaurang som ligger mitt i centrala Malm\u00f6, som inneb\u00e4r h\u00f6gt tempo. Vi har b\u00e5de lunch och a la cart\u00e9. \u00d6ppet alla dagar.\n\nVi s\u00f6ker er som har erfarenhet av det italienska k\u00f6ket. Du ska kunna laga mat till b\u00e5de lunch och a la cart\u00e9, g\u00f6ra best\u00e4llningar och menyer. H\u00e4r lagas allt fr\u00e5n grunden, och man f\u00f6rbereder allting sj\u00e4lv och \u00e4ven st\u00e4da och diska om det beh\u00f6vs.\n\nDu ska ha passion och \u00e4lska att laga mat. Du ska klara av mycket stress och gilla att arbeta. Du ska vara ansvarstagande, ordningsam, noggrann, lagspelare och kan \u00e4ven jobba sj\u00e4lvst\u00e4ndigt.\n\nJ\u00e4tte viktig tycker vi \u00e4r att du ska kunna regler om hygien och livsmedel.\n\nVi s\u00f6ker deltid och timanst\u00e4llning.\n\nPassar det in p\u00e5 er, maila ditt CV omg\u00e5ende.\n\nHelst ska du bo i Malm\u00f6, eller i n\u00e4rheten.", "annonstextFormaterad": "<p>Vi \u00e4r en italiensk restaurang som ligger mitt i centrala Malm\u00f6, som inneb\u00e4r h\u00f6gt tempo. Vi har b\u00e5de lunch och a la cart\u00e9. \u00d6ppet alla dagar.</p><p><br></p><p>Vi s\u00f6ker er som har erfarenhet av det italienska k\u00f6ket. Du ska kunna laga mat till b\u00e5de lunch och a la cart\u00e9, g\u00f6ra best\u00e4llningar och menyer. H\u00e4r lagas allt fr\u00e5n grunden, och man f\u00f6rbereder allting sj\u00e4lv och \u00e4ven st\u00e4da och diska om det beh\u00f6vs.</p><p>Du ska ha passion och \u00e4lska att laga mat. Du ska klara av mycket stress och gilla att arbeta. Du ska vara ansvarstagande, ordningsam, noggrann, lagspelare och kan \u00e4ven jobba sj\u00e4lvst\u00e4ndigt.</p><p>J\u00e4tte viktig tycker vi \u00e4r att du ska kunna regler om hygien och livsmedel.</p><p><br></p><p>Vi s\u00f6ker deltid och timanst\u00e4llning.</p><p><br></p><p>Passar det in p\u00e5 er, maila ditt CV omg\u00e5ende.</p><p>Helst ska du bo i Malm\u00f6, eller i n\u00e4rheten.</p>", "publiceringsdatum": "2021-03-16 10:58:07", "sistaPubliceringsdatum": "2021-05-15 23:59:59", "sistaAnsokningsdatum": "2021-05-15 23:59:59", "avpublicerad": false, "antalPlatser": 2, "anstallningTyp": {"varde": "PFZr_Syz_cUq", "namn": "Vanlig anst\u00e4llning"}, "varaktighetTyp": {"varde": "Xj7x_7yZ_jEn", "namn": "3 - 6 m\u00e5nader"}, "arbetstidTyp": {"varde": "947z_JGS_Uk2", "namn": "Deltid"}, "arbetstidOmfattningFran": 1.0, "lonTyp": {"varde": "oG8G_9cW_nRf", "namn": "Fast m\u00e5nads- vecko- eller timl\u00f6n"}, "organisationsnummer": "5567624795", "arbetsgivareId": "20820091", "arbetsgivareNamn": "Il Mondo AB", "arbetsplatsId": "83949782", "arbetsplatsNamn": "I1 MONDO I MALM\u00d6 AB", "ansokningssattEpost": " EMAIL ", "ansokningssattViaAF": false, "ejKravSvenskaEngelska": false, "inkluderande": false, "referens": "Kock", "yrkesroll": {"varde": "JbJw_as4_S93", "namn": "Kock, \u00e0 la carte"}, "ingenErfarenhetKravs": false, "yrkeserfarenheter": [{"varde": "JbJw_as4_S93", "namn": "Kock, \u00e0 la carte", "vikt": 10, "erfarenhetsniva": {"varde": "RWA2_uu6_udD", "namn": "2-4 \u00e5rs erfarenhet"}}], "tillgangTillEgenBil": false, "sprak": [{"varde": "zSLA_vw2_FXN", "namn": "Svenska", "vikt": 5}, {"varde": "b9cE_KXy_Yxv", "namn": "Italienska", "vikt": 5}, {"varde": "NVxJ_hLg_TYS", "namn": "Engelska", "vikt": 5}], "uppdateradTid": 1615888687106, "arbetsplatsadress": {"gatuadress": "STORTORGET 19", "postnr": "21134", "postort": "MALM\u00d6", "land": {"varde": "i46j_HmG_v64", "namn": "Sverige"}, "lan": {"varde": "CaRE_1nn_cSU", "namn": "Sk\u00e5ne l\u00e4n"}, "kommun": {"varde": "oYPt_yRA_Smm", "namn": "Malm\u00f6"}, "latitud": "55.60551608763431", "longitud": "12.999390077876475", "koordinatPrecision": "GATUADRESS"}, "informationAnsokningssatt": null, "telefonnummer": null, "kontaktpersoner": [{"fornamn": "Testy", "efternamn": "Testsson", "befattning": null, "telefonnummer": "+01011122233", "epost": "test@jobtechdev.se", "fackligRepresentant": false, "beskrivning": "blabla"}]}