{"annonsId": 24642362, "kallaTyp": "VIA_PLATSBANKEN_DXA", "version": "1.0", "externtAnnonsId": "46-556074-3089-34895436", "annonsrubrik": "Transformation Communication - Global Online Business", "annonstext": "Who are we?\nVolvo Cars is a company on a mission; to bring traditional car manufacturing into a connected, sustainable and smart future.\nSince 1927, we have been a brand known for our commitment to safety, creating innovative cars that make life less complicated for our consumers. In 2010, we decided to transform our business, resulting in a totally new generation of cars and technologies, as well as steady growth and record sales. Today, we\u2019re expanding our global footprint in Europe, China and the US, and we\u2019re on the lookout for new talent. \nWe are constantly pushing our own skills and abilities to drive change in the automobile industry like never before. We are looking for innovative, committed people to join us in this endeavour and create safe, sustainable and connected cars. We believe in the power of people and will challenge and support you to reach your full potential. Join us and be part of Volvo Cars\u2019 journey into the future.\r\n\r\nWhat do we offer?\nAt Global Online Business we are transforming our business model and are re-shaping the way we offer products to consumers. To support the execution of tactics, increase the speed to market and accelerate the commercial transformation, we are looking for a hands-on and creative communications person, focusing on internal communication to join our team.\n\nYou will report to the Head of Global Online Business Operations, work closely with the communication colleagues within the Commercial Operations Communications team, and all parts of the Global Online Business team.\n\nWhat you\u2019ll do\nIn this position, you will create a company-wide understanding of online sales and Global Online Business\u2019 role in the development and success of Volvo Cars and the commercial transformation we are facing. You will be empowering the Global Online Business teams by enabling dialogue, driving engagement and understanding through relevant communication and channels.\n\nYou will plan, develop, and manage tactical communication using clever editorial opportunities and smart digital tools. And your main areas of responsibility will be:\n  *  Handling Global Online Business internal communication strategy and planning (editorial, channels) and evaluate and measure communication initiatives.\n  *  Drive and deliver tactics related to the Global Online Business agenda such as weekly calls and newsletters and create content for presentations, videos, letters, webcasts, town halls etc. \n  *  Source stories for intranet and align with the Commercial Operations communications team.\n  *  Identify communication opportunities and coordinate a pool of ambassadors and speakers.\n  *  Map communication needs and to be the point of contact and the communications advisor within Global Online Business. This includes among other things to support in communications related to employer branding, recruitment, internal events and engagements.\n\nYou and your skills\nWe are looking for someone who is wickedly creative, digitally savvy and has proven skills in tactical communication (writing, planning, channels). You have relevant experience in communication and of course outstanding English skills.\n\nYou may have a degree in communication, but more importantly, you have worked with internal communication and are used to work in a changing environment, and understands the important role communication has within change management.\n\nWho are you?\nYou are a team player who thinks collaboration is an obvious key to success and networking comes naturally for you. We believe you are eager to capture the essence of our business strategy and to make it relevant for many, to create action and understanding. You see opportunities and grab them, and do not fear a fast-changing environment with tight deadlines.\n\nYou are of course curious and keen to listen and learn and eager to launch new and efficient ways of creating action and business through communication. Above all, what we\u2019re looking for is someone who will embody Volvo Cars' values as a caring, customer-centric organization and is passionate about converting our philosophy into actions and measurable results.\n\nLocation\nHQ Gothenburg or Stockholm\n\nWe are looking forward to your application\nPlease apply via the link no later than March 31th 2021, but don\u2019t wait with your application until the last minute because we are working with continuous selection and will start our screening before the last application date. In this recruitment, we use qualifying questions and will therefore not require any cover letter. Applications and CVs will not be accepted via email. If you have any questions you are welcome to contact Senior Recruiter FIRSTNAME LASTNAME.", "annonstextFormaterad": "Who are we?\nVolvo Cars is a company on a mission; to bring traditional car manufacturing into a connected, sustainable and smart future.\nSince 1927, we have been a brand known for our commitment to safety, creating innovative cars that make life less complicated for our consumers. In 2010, we decided to transform our business, resulting in a totally new generation of cars and technologies, as well as steady growth and record sales. Today, we\u2019re expanding our global footprint in Europe, China and the US, and we\u2019re on the lookout for new talent. \nWe are constantly pushing our own skills and abilities to drive change in the automobile industry like never before. We are looking for innovative, committed people to join us in this endeavour and create safe, sustainable and connected cars. We believe in the power of people and will challenge and support you to reach your full potential. Join us and be part of Volvo Cars\u2019 journey into the future.\r\n\r\nWhat do we offer?\nAt Global Online Business we are transforming our business model and are re-shaping the way we offer products to consumers. To support the execution of tactics, increase the speed to market and accelerate the commercial transformation, we are looking for a hands-on and creative communications person, focusing on internal communication to join our team.\n\nYou will report to the Head of Global Online Business Operations, work closely with the communication colleagues within the Commercial Operations Communications team, and all parts of the Global Online Business team.\n\nWhat you\u2019ll do\nIn this position, you will create a company-wide understanding of online sales and Global Online Business\u2019 role in the development and success of Volvo Cars and the commercial transformation we are facing. You will be empowering the Global Online Business teams by enabling dialogue, driving engagement and understanding through relevant communication and channels.\n\nYou will plan, develop, and manage tactical communication using clever editorial opportunities and smart digital tools. And your main areas of responsibility will be:\n  *  Handling Global Online Business internal communication strategy and planning (editorial, channels) and evaluate and measure communication initiatives.\n  *  Drive and deliver tactics related to the Global Online Business agenda such as weekly calls and newsletters and create content for presentations, videos, letters, webcasts, town halls etc.\u00a0\n  *  Source stories for intranet and align with the Commercial Operations communications team.\n  *  Identify communication opportunities and coordinate a\u00a0pool of ambassadors and speakers.\n  *  Map communication needs\u00a0and to be the point of contact and the communications advisor within Global Online Business. This includes among other things to support in communications related to employer branding, recruitment, internal events and engagements.\n\n\nYou and your skills\nWe are looking for someone who is wickedly creative, digitally savvy and has proven skills in tactical communication (writing, planning, channels). You have relevant experience in communication and of course outstanding English skills.\n\nYou may have a degree in communication, but more importantly, you have worked with internal communication and are used to work in a changing environment, and understands the important role communication has within change management.\n\nWho are you?\nYou are a team player who thinks collaboration is an obvious key to success and networking comes naturally for you. We believe you are eager to capture the essence of our business strategy and to make it relevant for many, to create action and understanding. You see opportunities and grab them, and do not fear a fast-changing environment with tight deadlines.\n\nYou are of course curious and keen to listen and learn and eager to launch new and efficient ways of creating action and business through communication. Above all, what we\u2019re looking for is someone who will embody Volvo Cars' values as a caring, customer-centric organization and is passionate about converting our philosophy into actions and measurable results.\n\nLocation\nHQ Gothenburg or Stockholm\n\nWe are looking forward to your application\nPlease apply via the link no later than March 31th 2021, but don\u2019t wait with your application until the last minute because we are working with continuous selection and will start our screening before the last application date. In this recruitment, we use qualifying questions and will therefore not require any cover letter. Applications and CVs will not be accepted via email. If you have any questions you are welcome to contact Senior Recruiter FIRSTNAME LASTNAME.", "publiceringsdatum": "2021-03-22 15:25:06", "sistaPubliceringsdatum": "2021-03-31 23:59:59", "sistaAnsokningsdatum": "2021-03-31 23:59:59", "avpublicerad": false, "antalPlatser": 1, "webbadress": "https://www.volvocars.com/", "villkorsbeskrivning": "Full Time\r\nUndefined", "anstallningTyp": {"varde": "PFZr_Syz_cUq", "namn": "Vanlig anst\u00e4llning"}, "varaktighetTyp": {"varde": "a7uU_j21_mkL", "namn": "Tillsvidare"}, "arbetstidTyp": {"varde": "6YE1_gAC_R2G", "namn": "Heltid"}, "lonTyp": {"varde": "oG8G_9cW_nRf", "namn": "Fast m\u00e5nads- vecko- eller timl\u00f6n"}, "lonebeskrivning": "Undefined", "organisationsnummer": "5560743089", "arbetsgivareId": "20342611", "arbetsgivareNamn": "Volvo Personvagnar AB", "arbetsplatsId": "0", "arbetsplatsNamn": "Volvo Car Corporation", "ansokningssattWebbadress": "https://volvo-car-corporation.contactrh.com/jobs/9669/34895436", "ansokningssattViaAF": false, "ejKravSvenskaEngelska": false, "inkluderande": false, "referens": "50231-34895436", "informationAnsokningssatt": "Ans\u00f6kan skickas till: VAK building, Assar Gabrielssons v\u00e4g, G\u00f6teborg, SE", "yrkesroll": {"varde": "64i5_ex4_BP9", "namn": "Kommunikationsstrateg"}, "ingenErfarenhetKravs": false, "yrkeserfarenheter": [{"varde": "64i5_ex4_BP9", "namn": "Kommunikationsstrateg", "vikt": 10, "erfarenhetsniva": {"varde": "yrAe_Fzi_E6u", "namn": "Mindre \u00e4n 1 \u00e5rs erfarenhet"}}], "tillgangTillEgenBil": false, "besoksadress": {"gatuadress": "Gothenburg", "postnr": null, "postort": null, "land": null}, "postadress": {"gatuadress": "Gothenburg", "postnr": "40531", "postort": "Gothenburg", "land": "SE"}, "ansokningsadress": {"gatuadress": "Gothenburg", "postnr": null, "postort": null, "land": null, "mottagare": null}, "uppdateradTid": 1616423106720, "arbetsplatsadress": {"gatuadress": null, "postnr": null, "postort": null, "land": {"varde": "i46j_HmG_v64", "namn": "Sverige"}, "lan": {"varde": "zdoY_6u5_Krt", "namn": "V\u00e4stra G\u00f6talands l\u00e4n"}, "kommun": {"varde": "PVZL_BQT_XtL", "namn": "G\u00f6teborg"}, "latitud": "57.70887", "longitud": "11.97456", "koordinatPrecision": "KOMMUN"}, "kontaktpersoner": [{"fornamn": "Testy", "efternamn": "Testsson", "befattning": null, "telefonnummer": "+01011122233", "epost": "test@jobtechdev.se", "fackligRepresentant": false, "beskrivning": "blabla"}], "telefonnummer": null, "ansokningssattEpost": null}